fnl_aws_cdk/__init__.py
fnl_aws_cdk/py.typed
fnl_aws_cdk/_jsii/__init__.py
fnl_aws_cdk/_jsii/fnl-aws-cdk@1.8.0.jsii.tgz
fnl_aws_cdk-1.8.0.dist-info/LICENSE
fnl_aws_cdk-1.8.0.dist-info/METADATA
fnl_aws_cdk-1.8.0.dist-info/WHEEL
fnl_aws_cdk-1.8.0.dist-info/top_level.txt
fnl_aws_cdk-1.8.0.dist-info/RECORD
