Metadata-Version: 2.1
Name: fnl-aws-cdk
Version: 1.8.0
Summary: A collection of AWS CDK Constructs designed by and for the FNL team.
Home-page: https://github.com/colemandevries/fnl-aws-cdk.git
Author: Cole DeVries<devriesca@nih.gov>
License: Apache-2.0
Project-URL: Source, https://github.com/colemandevries/fnl-aws-cdk.git
Classifier: Intended Audience :: Developers
Classifier: Operating System :: OS Independent
Classifier: Programming Language :: JavaScript
Classifier: Programming Language :: Python :: 3 :: Only
Classifier: Programming Language :: Python :: 3.9
Classifier: Programming Language :: Python :: 3.10
Classifier: Programming Language :: Python :: 3.11
Classifier: Typing :: Typed
Classifier: Development Status :: 5 - Production/Stable
Classifier: License :: OSI Approved
Requires-Python: ~=3.9
License-File: LICENSE
Requires-Dist: aws-cdk-lib<3.0.0,>=2.203.1
Requires-Dist: constructs<11.0.0,>=10.0.5
Requires-Dist: jsii<2.0.0,>=1.112.0
Requires-Dist: publication>=0.0.3
Requires-Dist: typeguard<4.3.0,>=2.13.3
